umadb/__init__.py
umadb/_umadb.abi3.so
umadb/_umadb.pyi
umadb/py.typed
umadb-0.3.3.dist-info/METADATA
umadb-0.3.3.dist-info/WHEEL
umadb-0.3.3.dist-info/RECORD
