Metadata-Version: 2.4
Name: umadb
Version: 0.3.3
Classifier: Development Status :: 3 - Alpha
Classifier: Intended Audience :: Developers
Classifier: License :: OSI Approved :: MIT License
Classifier: License :: OSI Approved :: Apache Software License
Classifier: Programming Language :: Python :: 3
Classifier: Programming Language :: Python :: 3.10
Classifier: Programming Language :: Python :: 3.11
Classifier: Programming Language :: Python :: 3.12
Classifier: Programming Language :: Python :: 3.13
Classifier: Programming Language :: Python :: 3.14
Classifier: Programming Language :: Rust
Classifier: Topic :: Database
Summary: Python client for UmaDB event store
Keywords: event-store,grpc,client,database
Home-Page: https://umadb.io
Author-email: John Bywater <john.bywater@appropriatesoftware.net>
License: MIT OR Apache-2.0
Requires-Python: >=3.10
Project-URL: Homepage, https://umadb.io
Project-URL: Repository, https://github.com/umadb-io/umadb
